<?xml version="1.0" encoding="utf-8"?>
	<annotation>
		<folder>trainData</folder>
		<filename>original_box_0027.jpg</filename>
		<path>original_box_0027.jpg</path>
		<source>
			<database>Unknown</database>
		</source>
		<size>
			<width>512</width>
			<height>512</height>
			<depth>3</depth>
		</size>
		<segmented>0</segmented>
		<object>
			<name>0</name>
			<pose>Unspecified</pose>
			<truncated>0</truncated>
			<difficult>0</difficult>
			<bndbox>
				<xmin>277</xmin>
				<ymin>257</ymin>
				<xmax>509</xmax>
				<ymax>505</ymax>
			</bndbox>
		</object>
		<object>
			<name>0</name>
			<pose>Unspecified</pose>
			<truncated>0</truncated>
			<difficult>0</difficult>
			<bndbox>
				<xmin>39</xmin>
				<ymin>3</ymin>
				<xmax>214</xmax>
				<ymax>131</ymax>
			</bndbox>
		</object>
	</annotation>
