<?xml version="1.0" encoding="utf-8"?>
	<annotation>
		<folder>trainData</folder>
		<filename>original_box_0075.jpg</filename>
		<path>original_box_0075.jpg</path>
		<source>
			<database>Unknown</database>
		</source>
		<size>
			<width>512</width>
			<height>512</height>
			<depth>3</depth>
		</size>
		<segmented>0</segmented>
		<object>
			<name>0</name>
			<pose>Unspecified</pose>
			<truncated>0</truncated>
			<difficult>0</difficult>
			<bndbox>
				<xmin>261</xmin>
				<ymin>194</ymin>
				<xmax>328</xmax>
				<ymax>256</ymax>
			</bndbox>
		</object>
		<object>
			<name>0</name>
			<pose>Unspecified</pose>
			<truncated>0</truncated>
			<difficult>0</difficult>
			<bndbox>
				<xmin>208</xmin>
				<ymin>211</ymin>
				<xmax>280</xmax>
				<ymax>274</ymax>
			</bndbox>
		</object>
		<object>
			<name>0</name>
			<pose>Unspecified</pose>
			<truncated>0</truncated>
			<difficult>0</difficult>
			<bndbox>
				<xmin>108</xmin>
				<ymin>253</ymin>
				<xmax>213</xmax>
				<ymax>308</ymax>
			</bndbox>
		</object>
		<object>
			<name>0</name>
			<pose>Unspecified</pose>
			<truncated>0</truncated>
			<difficult>0</difficult>
			<bndbox>
				<xmin>79</xmin>
				<ymin>286</ymin>
				<xmax>142</xmax>
				<ymax>328</ymax>
			</bndbox>
		</object>
	</annotation>
